{
  "lastUpdated": "2025-09-27T10:52:22.998Z",
  "oscPort": 19100,
  "oscHost": "127.0.0.1",
  "enableDefaultEndpoints": true,
  "oscMessageFormat": "string",
  "webUI": {
    "port": 19101,
    "autoStart": true,
    "theme": "default"
  },
  "messageProcessing": {
    "maxMessages": 100,
    "enableDebugLogging": true,
    "logIncomingMessages": true,
    "logOutgoingMessages": true
  },
  "ruleEngine": {
    "enableCustomRules": true,
    "maxRules": 50,
    "defaultConditionLogic": "AND",
    "defaultGroupLogic": "OR"
  },
  "ui": {
    "lastActiveTab": "overview",
    "showNotifications": true,
    "notificationDuration": 5000,
    "autoRefreshLogs": true,
    "logsRefreshInterval": 2000,
    "enableAnimations": true,
    "compactMode": false
  },
  "export": {
    "includeSystemInfo": true,
    "includeRules": true,
    "includeConfiguration": true,
    "includeMessageLogs": false
  },
  "advanced": {
    "oscReconnectInterval": 5000,
    "maxReconnectAttempts": 3,
    "messageQueueSize": 1000,
    "enableConnectionHealthCheck": true,
    "connectionHealthCheckInterval": 30000
  }
}